[
  {
    "title": "Dragon Art_L1",
    "link_thumb": "https://live.staticflickr.com/65535/51780815254_7caa408307_o.gif",
    "id_album": "2059013998",
    "total": 13,
    "size_max_detail_page": 1,
    "list_detail": [
      {
        "index_page": 0,
        "link_page": "https://github.com/lmbstudiocontact/mb5_dt_alb_0/raw/main/14132021_dta_2059013998_index_0.json"
      }
    ]
  },
  {
    "title": "Pooh_L7",
    "link_thumb": "https://live.staticflickr.com/65535/51704142005_6d98244141_o.gif",
    "id_album": "1269389010",
    "total": 9,
    "size_max_detail_page": 1,
    "list_detail": [
      {
        "index_page": 0,
        "link_page": "https://github.com/lmbstudiocontact/mb5_dt_alb_0/raw/main/14132021_dta_1269389010_index_0.json"
      }
    ]
  },
  {
    "title": "Simpsons Cartoon_L5",
    "link_thumb": "https://live.staticflickr.com/65535/51780963369_9ff0c046e1_n.jpg",
    "id_album": "1276946592",
    "total": 8,
    "size_max_detail_page": 1,
    "list_detail": [
      {
        "index_page": 0,
        "link_page": "https://github.com/lmbstudiocontact/mb5_dt_alb_0/raw/main/14132021_dta_1276946592_index_0.json"
      }
    ]
  },
  {
    "title": "Rio 2_L3",
    "link_thumb": "https://live.staticflickr.com/65535/51781155450_e8d861a3da_n.jpg",
    "id_album": "-1210862916",
    "total": 17,
    "size_max_detail_page": 1,
    "list_detail": [
      {
        "index_page": 0,
        "link_page": "https://github.com/lmbstudiocontact/mb5_dt_alb_0/raw/main/14132021_dta_-1210862916_index_0.json"
      }
    ]
  },
  {
    "title": "Mickey Cartoon_L5",
    "link_thumb": "https://live.staticflickr.com/65535/51780912559_f98d459137_o.gif",
    "id_album": "1680949826",
    "total": 22,
    "size_max_detail_page": 1,
    "list_detail": [
      {
        "index_page": 0,
        "link_page": "https://github.com/lmbstudiocontact/mb5_dt_alb_0/raw/main/14132021_dta_1680949826_index_0.json"
      }
    ]
  },
  {
    "title": "Seven deadly sins Anime_L1",
    "link_thumb": "https://live.staticflickr.com/65535/51780331376_943f9edd5c_n.jpg",
    "id_album": "1802210937",
    "total": 43,
    "size_max_detail_page": 1,
    "list_detail": [
      {
        "index_page": 0,
        "link_page": "https://github.com/lmbstudiocontact/mb5_dt_alb_0/raw/main/14132021_dta_1802210937_index_0.json"
      }
    ]
  },
  {
    "title": "Spider Man Cartoon_L5",
    "link_thumb": "https://live.staticflickr.com/65535/51780545388_3738459013_n.jpg",
    "id_album": "1735002395",
    "total": 16,
    "size_max_detail_page": 1,
    "list_detail": [
      {
        "index_page": 0,
        "link_page": "https://github.com/lmbstudiocontact/mb5_dt_alb_0/raw/main/14132021_dta_1735002395_index_0.json"
      }
    ]
  },
  {
    "title": "Animal_L7",
    "link_thumb": "https://live.staticflickr.com/65535/51694649666_d4bf939298_o.gif",
    "id_album": "-1172738450",
    "total": 28,
    "size_max_detail_page": 1,
    "list_detail": [
      {
        "index_page": 0,
        "link_page": "https://github.com/lmbstudiocontact/mb5_dt_alb_0/raw/main/14132021_dta_-1172738450_index_0.json"
      }
    ]
  },
  {
    "title": "Death Note Anime_L5",
    "link_thumb": "https://live.staticflickr.com/65535/51780806214_feb2982173_o.gif",
    "id_album": "-374116170",
    "total": 8,
    "size_max_detail_page": 1,
    "list_detail": [
      {
        "index_page": 0,
        "link_page": "https://github.com/lmbstudiocontact/mb5_dt_alb_0/raw/main/14132021_dta_-374116170_index_0.json"
      }
    ]
  }
]