[
  {
    "title": "Animal_L7",
    "link_thumb": "https://live.staticflickr.com/65535/51694649666_d4bf939298_o.gif",
    "id_album": "-1172738450",
    "total": 28,
    "size_max_detail_page": 1,
    "list_detail": [
      {
        "index_page": 0,
        "link_page": "https://github.com/lmbstudiocontact/mb5_dt_alb_0/raw/main/14132021_dta_-1172738450_index_0.json"
      }
    ]
  },
  {
    "title": "Ratatouille Cartoon_L1",
    "link_thumb": "https://live.staticflickr.com/65535/51704058109_89dd676b37_o.gif",
    "id_album": "1746345500",
    "total": 5,
    "size_max_detail_page": 1,
    "list_detail": [
      {
        "index_page": 0,
        "link_page": "https://github.com/lmbstudiocontact/mb5_dt_alb_0/raw/main/14132021_dta_1746345500_index_0.json"
      }
    ]
  },
  {
    "title": "Birds_L6",
    "link_thumb": "https://live.staticflickr.com/65535/51694011512_2a5cf1581f_o.gif",
    "id_album": "1119566095",
    "total": 1,
    "size_max_detail_page": 1,
    "list_detail": [
      {
        "index_page": 0,
        "link_page": "https://github.com/lmbstudiocontact/mb5_dt_alb_0/raw/main/14132021_dta_1119566095_index_0.json"
      }
    ]
  },
  {
    "title": "Music_L4",
    "link_thumb": "https://live.staticflickr.com/65535/51701760470_c753b7400b_o.gif",
    "id_album": "908522978",
    "total": 24,
    "size_max_detail_page": 1,
    "list_detail": [
      {
        "index_page": 0,
        "link_page": "https://github.com/lmbstudiocontact/mb5_dt_alb_0/raw/main/14132021_dta_908522978_index_0.json"
      }
    ]
  },
  {
    "title": "Simpsons Cartoon_L2",
    "link_thumb": "https://live.staticflickr.com/65535/51702934927_8dc061d636_o.gif",
    "id_album": "1276946589",
    "total": 8,
    "size_max_detail_page": 1,
    "list_detail": [
      {
        "index_page": 0,
        "link_page": "https://github.com/lmbstudiocontact/mb5_dt_alb_0/raw/main/14132021_dta_1276946589_index_0.json"
      }
    ]
  },
  {
    "title": "Scenery",
    "link_thumb": "https://live.staticflickr.com/65535/51693995721_0f1d731c19_o.gif",
    "id_album": "-715666509",
    "total": 2,
    "size_max_detail_page": 1,
    "list_detail": [
      {
        "index_page": 0,
        "link_page": "https://github.com/lmbstudiocontact/mb5_dt_alb_0/raw/main/14132021_dta_-715666509_index_0.json"
      }
    ]
  },
  {
    "title": "Mocmoc_L7",
    "link_thumb": "https://live.staticflickr.com/65535/51700880313_2d59e3c6d3_o.gif",
    "id_album": "-661938806",
    "total": 31,
    "size_max_detail_page": 1,
    "list_detail": [
      {
        "index_page": 0,
        "link_page": "https://github.com/lmbstudiocontact/mb5_dt_alb_0/raw/main/14132021_dta_-661938806_index_0.json"
      }
    ]
  },
  {
    "title": "Doraemon Anime_L3",
    "link_thumb": "https://live.staticflickr.com/65535/51697708745_94b365859e_o.gif",
    "id_album": "405661393",
    "total": 16,
    "size_max_detail_page": 1,
    "list_detail": [
      {
        "index_page": 0,
        "link_page": "https://github.com/lmbstudiocontact/mb5_dt_alb_0/raw/main/14132021_dta_405661393_index_0.json"
      }
    ]
  },
  {
    "title": "Lilo & Stitch Cartoon_L5",
    "link_thumb": "https://live.staticflickr.com/65535/51700623949_37b7f8a054_o.gif",
    "id_album": "685543663",
    "total": 30,
    "size_max_detail_page": 1,
    "list_detail": [
      {
        "index_page": 0,
        "link_page": "https://github.com/lmbstudiocontact/mb5_dt_alb_0/raw/main/14132021_dta_685543663_index_0.json"
      }
    ]
  }
]