[
  {
    "title": "One Punch Man Anime_L3",
    "link_thumb": "https://live.staticflickr.com/65535/51701890501_cf0ccc5e48_o.gif",
    "id_album": "-1626855612",
    "total": 2,
    "size_max_detail_page": 1,
    "list_detail": [
      {
        "index_page": 0,
        "link_page": "https://github.com/lmbstudiocontact/mb5_dt_alb_0/raw/main/14132021_dta_-1626855612_index_0.json"
      }
    ]
  },
  {
    "title": "Naruto Anime_L2",
    "link_thumb": "https://live.staticflickr.com/65535/51701683814_9c5931f009_o.gif",
    "id_album": "1894397984",
    "total": 37,
    "size_max_detail_page": 1,
    "list_detail": [
      {
        "index_page": 0,
        "link_page": "https://github.com/lmbstudiocontact/mb5_dt_alb_0/raw/main/14132021_dta_1894397984_index_0.json"
      }
    ]
  },
  {
    "title": "Birds_L6",
    "link_thumb": "https://live.staticflickr.com/65535/51694011512_2a5cf1581f_o.gif",
    "id_album": "1119566095",
    "total": 1,
    "size_max_detail_page": 1,
    "list_detail": [
      {
        "index_page": 0,
        "link_page": "https://github.com/lmbstudiocontact/mb5_dt_alb_0/raw/main/14132021_dta_1119566095_index_0.json"
      }
    ]
  },
  {
    "title": "Doraemon Anime_L5",
    "link_thumb": "https://live.staticflickr.com/65535/51697535724_1b5b06e50c_o.gif",
    "id_album": "405661395",
    "total": 16,
    "size_max_detail_page": 1,
    "list_detail": [
      {
        "index_page": 0,
        "link_page": "https://github.com/lmbstudiocontact/mb5_dt_alb_0/raw/main/14132021_dta_405661395_index_0.json"
      }
    ]
  },
  {
    "title": "Kitty & My Melody_L4",
    "link_thumb": "https://live.staticflickr.com/65535/51699356096_9ae549bf17_o.gif",
    "id_album": "-378480542",
    "total": 76,
    "size_max_detail_page": 2,
    "list_detail": [
      {
        "index_page": 0,
        "link_page": "https://github.com/lmbstudiocontact/mb5_dt_alb_0/raw/main/14132021_dta_-378480542_index_0.json"
      },
      {
        "index_page": 1,
        "link_page": "https://github.com/lmbstudiocontact/mb5_dt_alb_0/raw/main/14132021_dta_-378480542_index_1.json"
      }
    ]
  },
  {
    "title": "Plants Vs Zombies_L2",
    "link_thumb": "https://live.staticflickr.com/65535/51702758503_597f6699e6_o.gif",
    "id_album": "-1426777469",
    "total": 24,
    "size_max_detail_page": 1,
    "list_detail": [
      {
        "index_page": 0,
        "link_page": "https://github.com/lmbstudiocontact/mb5_dt_alb_0/raw/main/14132021_dta_-1426777469_index_0.json"
      }
    ]
  },
  {
    "title": "Madagascar Cartoon_L1",
    "link_thumb": "https://live.staticflickr.com/65535/51699314367_ddca91c8f5_o.gif",
    "id_album": "-2014542390",
    "total": 9,
    "size_max_detail_page": 1,
    "list_detail": [
      {
        "index_page": 0,
        "link_page": "https://github.com/lmbstudiocontact/mb5_dt_alb_0/raw/main/14132021_dta_-2014542390_index_0.json"
      }
    ]
  },
  {
    "title": "Football_L5",
    "link_thumb": "https://live.staticflickr.com/65535/51697669326_d35721f31b_o.gif",
    "id_album": "-371026085",
    "total": 49,
    "size_max_detail_page": 1,
    "list_detail": [
      {
        "index_page": 0,
        "link_page": "https://github.com/lmbstudiocontact/mb5_dt_alb_0/raw/main/14132021_dta_-371026085_index_0.json"
      }
    ]
  },
  {
    "title": "Peace Art_L7",
    "link_thumb": "https://live.staticflickr.com/65535/51702387681_14580ae1f0_o.gif",
    "id_album": "437172985",
    "total": 34,
    "size_max_detail_page": 1,
    "list_detail": [
      {
        "index_page": 0,
        "link_page": "https://github.com/lmbstudiocontact/mb5_dt_alb_0/raw/main/14132021_dta_437172985_index_0.json"
      }
    ]
  }
]