[
  {
    "title": "Madagascar Cartoon_L1",
    "link_thumb": "https://live.staticflickr.com/65535/51780873669_3c4c2e4909_o.gif",
    "id_album": "-2014542390",
    "total": 9,
    "size_max_detail_page": 1,
    "list_detail": [
      {
        "index_page": 0,
        "link_page": "https://github.com/lmbstudiocontact/mb5_dt_alb_0/raw/main/14132021_dta_-2014542390_index_0.json"
      }
    ]
  },
  {
    "title": "Kitty & My Melody_L4",
    "link_thumb": "https://live.staticflickr.com/65535/51779377932_cab4e1b515_o.gif",
    "id_album": "-378480542",
    "total": 76,
    "size_max_detail_page": 2,
    "list_detail": [
      {
        "index_page": 0,
        "link_page": "https://github.com/lmbstudiocontact/mb5_dt_alb_0/raw/main/14132021_dta_-378480542_index_0.json"
      },
      {
        "index_page": 1,
        "link_page": "https://github.com/lmbstudiocontact/mb5_dt_alb_0/raw/main/14132021_dta_-378480542_index_1.json"
      }
    ]
  },
  {
    "title": "Death Note Anime_L4",
    "link_thumb": "https://live.staticflickr.com/65535/51779350467_e4048203f0_o.gif",
    "id_album": "-374116171",
    "total": 8,
    "size_max_detail_page": 1,
    "list_detail": [
      {
        "index_page": 0,
        "link_page": "https://github.com/lmbstudiocontact/mb5_dt_alb_0/raw/main/14132021_dta_-374116171_index_0.json"
      }
    ]
  },
  {
    "title": "Butterfly_L4",
    "link_thumb": "https://live.staticflickr.com/65535/51696199260_013e69abc9_o.gif",
    "id_album": "657564372",
    "total": 6,
    "size_max_detail_page": 1,
    "list_detail": [
      {
        "index_page": 0,
        "link_page": "https://github.com/lmbstudiocontact/mb5_dt_alb_0/raw/main/14132021_dta_657564372_index_0.json"
      }
    ]
  },
  {
    "title": "Madagascar Cartoon_L4",
    "link_thumb": "https://live.staticflickr.com/65535/51780472278_38fe3929b5_o.gif",
    "id_album": "-2014542387",
    "total": 9,
    "size_max_detail_page": 1,
    "list_detail": [
      {
        "index_page": 0,
        "link_page": "https://github.com/lmbstudiocontact/mb5_dt_alb_0/raw/main/14132021_dta_-2014542387_index_0.json"
      }
    ]
  },
  {
    "title": "Smurf Houses Cartoon_L5",
    "link_thumb": "https://live.staticflickr.com/65535/51780563898_1e63173f6d_n.jpg",
    "id_album": "228264854",
    "total": 4,
    "size_max_detail_page": 1,
    "list_detail": [
      {
        "index_page": 0,
        "link_page": "https://github.com/lmbstudiocontact/mb5_dt_alb_0/raw/main/14132021_dta_228264854_index_0.json"
      }
    ]
  },
  {
    "title": "Halloween Ghost Witch_L5",
    "link_thumb": "https://live.staticflickr.com/65535/51781113565_de90f89cc2_o.gif",
    "id_album": "1746571237",
    "total": 49,
    "size_max_detail_page": 1,
    "list_detail": [
      {
        "index_page": 0,
        "link_page": "https://github.com/lmbstudiocontact/mb5_dt_alb_0/raw/main/14132021_dta_1746571237_index_0.json"
      }
    ]
  },
  {
    "title": "Guns",
    "link_thumb": "https://live.staticflickr.com/65535/51694645284_2fb993ba34_o.gif",
    "id_album": "2231123",
    "total": 10,
    "size_max_detail_page": 1,
    "list_detail": [
      {
        "index_page": 0,
        "link_page": "https://github.com/lmbstudiocontact/mb5_dt_alb_0/raw/main/14132021_dta_2231123_index_0.json"
      }
    ]
  },
  {
    "title": "Dog_L6",
    "link_thumb": "https://live.staticflickr.com/65535/51696759131_97a8cd7b65_o.gif",
    "id_album": "2052455277",
    "total": 22,
    "size_max_detail_page": 1,
    "list_detail": [
      {
        "index_page": 0,
        "link_page": "https://github.com/lmbstudiocontact/mb5_dt_alb_0/raw/main/14132021_dta_2052455277_index_0.json"
      }
    ]
  }
]